setup.py
extranormal3/__init__.py
extranormal3/curved_tools.py
extranormal3/extra_exafs.py
extranormal3/forward_fourier.py
extranormal3/normal_xas.py
extranormal3.egg-info/PKG-INFO
extranormal3.egg-info/SOURCES.txt
extranormal3.egg-info/dependency_links.txt
extranormal3.egg-info/top_level.txt
scripts/ab_test.py