Metadata-Version: 1.0
Name: extranormal3
Version: 0.0.1
Summary: Quick normalization of a bunch of Quick-EXAFS spectra
Home-page: UNKNOWN
Author: Olga Roudenko
Author-email: olga.roudenko@synchrotron-soleil.fr
License: GPL >= v.3
Platform: Linux
Platform: Windows
